scaffold_kit/__init__.py
scaffold_kit/__version__.py
scaffold_kit/__version__.pyi
scaffold_kit/checklist.py
scaffold_kit/config.py
scaffold_kit/init.py
scaffold_kit/main.py
scaffold_kit/scaffold.py
scaffold_kit/tree.py
scaffold_kit/examples/.scaffoldignore
scaffold_kit/examples/configs/.scaffoldkitrc
scaffold_kit/examples/configs/.scaffoldkitrc.json
scaffold_kit/examples/configs/.scaffoldkitrc.yaml
scaffold_kit/examples/configs/scaffoldkitrc.json
scaffold_kit/examples/configs/scaffoldkitrc.yaml
scaffold_kit/examples/scaffold/scaffold.json
scaffold_kit/examples/scaffold/scaffold.yaml
scaffold_kit/utils/__init__.py
scaffold_kit/utils/ignore_parser.py
scaffold_kit/utils/pattern_processor.py
scaffold_kit/utils/string_utils.py
scaffold_kit-1.0.1.dist-info/METADATA
scaffold_kit-1.0.1.dist-info/WHEEL
scaffold_kit-1.0.1.dist-info/entry_points.txt
scaffold_kit-1.0.1.dist-info/licenses/LICENSE
scaffold_kit-1.0.1.dist-info/RECORD
