Metadata-Version: 2.4
Name: scaffold-kit
Version: 1.0.1
Summary: Command-line tools for project setup, structure creation, file tracking, and directory trees.
Project-URL: Homepage, https://github.com/sidisinsane/scaffold-kit
Project-URL: Documentation, https://sidisinsane.github.io/scaffold-kit/
Project-URL: API Reference, https://sidisinsane.github.io/scaffold-kit/reference/
Project-URL: Repository, https://github.com/sidisinsane/scaffold-kit.git
Project-URL: Bug Tracker, https://github.com/sidisinsane/scaffold-kit/issues
Author-email: Dirk Sidney Jansen <sidisinsane@users.noreply.github.com>
License-Expression: MIT
License-File: LICENSE
Keywords: cli,cli-tool,command-line,command-line-tool,directory-tree,file-tree,generator,productivity,project-structure,scaffold,tree
Classifier: Development Status :: 4 - Beta
Classifier: Intended Audience :: Developers
Classifier: License :: OSI Approved :: MIT License
Classifier: Operating System :: OS Independent
Classifier: Programming Language :: Python :: 3
Classifier: Programming Language :: Python :: 3.12
Classifier: Programming Language :: Python :: 3.13
Classifier: Topic :: Software Development :: Code Generators
Classifier: Topic :: System :: Filesystems
Classifier: Topic :: Utilities
Requires-Python: >=3.12
Requires-Dist: pyyaml~=6.0.2
Provides-Extra: build
Requires-Dist: python-semantic-release~=10.3.1; extra == 'build'
Provides-Extra: dev
Requires-Dist: bandit~=1.8.6; extra == 'dev'
Requires-Dist: coverage~=7.10.1; extra == 'dev'
Requires-Dist: mypy~=1.17.0; extra == 'dev'
Requires-Dist: pre-commit~=4.3.0; extra == 'dev'
Requires-Dist: pylint~=3.3.8; extra == 'dev'
Requires-Dist: pytest-cov~=6.2.1; extra == 'dev'
Requires-Dist: pytest~=8.4.1; extra == 'dev'
Requires-Dist: ruff~=0.12.10; extra == 'dev'
Requires-Dist: taplo~=0.9.3; extra == 'dev'
Requires-Dist: yamllint~=1.37.1; extra == 'dev'
Provides-Extra: docs
Requires-Dist: mkdocs-gen-files~=0.5.0; extra == 'docs'
Requires-Dist: mkdocs-material~=9.6.16; extra == 'docs'
Requires-Dist: mkdocs-nav-weight~=0.2.0; extra == 'docs'
Requires-Dist: mkdocs-section-index~=0.3.10; extra == 'docs'
Requires-Dist: mkdocstrings[python]~=0.30.0; extra == 'docs'
Requires-Dist: mkdocs~=1.6.1; extra == 'docs'
Requires-Dist: pymdown-extensions~=10.16.1; extra == 'docs'
Requires-Dist: sphinx-favicon~=1.0.1; extra == 'docs'
Requires-Dist: sphinx~=8.2.3; extra == 'docs'
Provides-Extra: test
Requires-Dist: coverage~=7.10.1; extra == 'test'
Requires-Dist: pytest-cov~=6.2.1; extra == 'test'
Requires-Dist: pytest~=8.4.1; extra == 'test'
